tmh/__init__.py
tmh/audio_embeddings.py
tmh/foo.py
tmh/generate_code.py
tmh/generated.py
tmh/get_image.py
tmh/language_files.py
tmh/multi.py
tmh/overlap.py
tmh/phonemes.py
tmh/separate_speakers.py
tmh/speech_generation.py
tmh/swedish_phonemizer.py
tmh/test_transcribe.py
tmh/transcribe.py
tmh/transcribe_with_lm.py
tmh/transcribe_with_vad.py
tmh/utils.py
tmh/vad.py
tmh/beskow/__init__.py
tmh/beskow/mapdict.py
tmh/beskow/phonemap.py
tmh/beskow/phonemap.test.py
tmh/beskow/phonemap.tsv
tmh/images/__init__.py
tmh/images/stable_diffusion.py
tmh/images/stable_diffusion.test.py
tmh/speech/__init__.py
tmh/speech/base_speech_model.py
tmh/speech/tacotron.py
tmh/text/__init__.py
tmh/text/get_embeddings.py
tmh/text/ner.py
tmh/text/question_answering.py
tmh/text/sentiment_analysis.py
tmh/text/summarization.py
tmh/text/text_generation.py
tmh/text/translate.py
tmh/text/zero_shot.py
tmh-0.0.109.dist-info/LICENSE
tmh-0.0.109.dist-info/METADATA
tmh-0.0.109.dist-info/WHEEL
tmh-0.0.109.dist-info/top_level.txt
tmh-0.0.109.dist-info/RECORD
