Metadata-Version: 2.1
Name: tmh
Version: 0.0.109
Summary: TMH Speech package
Home-page: https://gits-15.sys.kth.se/bmoell/tmh
Author: Birger Moell, Ambika Kirkland, Johan Boye, Harm Lameris, August Erseus
Author-email: <bmoell@kth.se>
Project-URL: Bug Tracker, https://gits-15.sys.kth.se/bmoell/tmh/issues
Keywords: python,speech,voice,nlp
Classifier: Development Status :: 1 - Planning
Classifier: Intended Audience :: Developers
Classifier: Programming Language :: Python :: 3
Classifier: Operating System :: Unix
Classifier: Operating System :: MacOS :: MacOS X
Classifier: Operating System :: Microsoft :: Windows
License-File: LICENSE
Requires-Dist: transformers
Requires-Dist: diffusers
Requires-Dist: torch
Requires-Dist: torchaudio
Requires-Dist: speechbrain
Requires-Dist: librosa
Requires-Dist: noisereduce
Requires-Dist: numpy
Requires-Dist: scipy
Requires-Dist: unidecode
Requires-Dist: inflect
Requires-Dist: python-dotenv
Requires-Dist: deep-phonemizer
Requires-Dist: argparse
Requires-Dist: pydub
Requires-Dist: pyctcdecode
